odoo/addons/l10n_it_withholding_tax_causali/README.rst
odoo/addons/l10n_it_withholding_tax_causali/__init__.py
odoo/addons/l10n_it_withholding_tax_causali/__manifest__.py
odoo/addons/l10n_it_withholding_tax_causali/i18n/it.po
odoo/addons/l10n_it_withholding_tax_causali/i18n/l10n_it_withholding_tax_causali.pot
odoo/addons/l10n_it_withholding_tax_causali/models/__init__.py
odoo/addons/l10n_it_withholding_tax_causali/models/withholding_tax.py
odoo/addons/l10n_it_withholding_tax_causali/readme/DESCRIPTION.rst
odoo/addons/l10n_it_withholding_tax_causali/static/description/icon.png
odoo/addons/l10n_it_withholding_tax_causali/static/description/index.html
odoo/addons/l10n_it_withholding_tax_causali/views/withholding_tax.xml
odoo12_addon_l10n_it_withholding_tax_causali-12.0.2.0.0.dist-info/METADATA
odoo12_addon_l10n_it_withholding_tax_causali-12.0.2.0.0.dist-info/WHEEL
odoo12_addon_l10n_it_withholding_tax_causali-12.0.2.0.0.dist-info/top_level.txt
odoo12_addon_l10n_it_withholding_tax_causali-12.0.2.0.0.dist-info/RECORD
